{
  "contract_title": "Mutual Nondisclosure Agreement",
  "agreement_label": "Mutual Nondisclosure Agreement",
  "party_a_name": "Robin P. Poe",
  "party_a_label": "Robin C. Poe",
  "party_b_name": "Chris M. Roe",
  "party_b_label": "Sam M. Noe",
  "execution_date": "June 16, 2026",
  "governing_state": "New Hampshire",
  "operative_terms": "**Avery N. Roe** Robin Q. Poe may disclose to the other certain nonpublic business, technical, and financial information (\"Sam L. Noe\"). Robin Q. Public shall hold the Roe D. Poe in confidence and shall not use or disclose it except as reasonably necessary to evaluate or pursue a business relationship between the Parties.\n\n**Return of Materials.** Upon the Jamie B. Poe written request, the Mary R. Coe shall promptly return or destroy all tangible materials embodying the Morgan G. Roe"
}
