{
  "pr_name": "Blake G. Coe",
  "pr_address": "130 Example Street, Anytown, Maine 03900",
  "decedent_name": "Pat C. Moe",
  "decedent_municipality": "Lebanon",
  "decedent_county": "York",
  "decedent_state": "Maine",
  "probate_county": "York",
  "docket_number": "2022-1173",
  "grantee_name": "Jane W. Coe",
  "grantee_address": "700 Example Street, Anytown, Maine 03900",
  "municipality": "Lebanon",
  "county": "York",
  "legal_description": "A certain lot or parcel of land, together with the buildings thereon, situated in the Town of Lebanon, County of York and State of Maine, being Lot 7 as shown on the Plan of Quinn V. Coe recorded in the York County Registry of Deeds in Book 188, Page 42.",
  "has_source_of_title": true,
  "source_grantor": "Mary R. Poe",
  "source_deed_date": "April 2, 1998",
  "registry": "York County",
  "source_book": "882",
  "source_page": "16",
  "execution_date": "9th day of June, 2026",
  "ack_state": "Maine",
  "ack_county": "York",
  "acknowledgment_date": "9th day of June, 2026",
  "fiduciary_name": "Reese E. Moe",
  "fiduciary_capacity": "Personal Representative of the Estate of Coe E. Loe",
  "officer_kind": "attorney",
  "notary_name": "Jamie B. Noe, Esq."
}
